xgpr.libs/libgomp-a34b3233.so.1.0.0
xgpr-0.4.8.5.dist-info/WHEEL
xgpr-0.4.8.5.dist-info/RECORD
xgpr-0.4.8.5.dist-info/METADATA
xgpr-0.4.8.5.dist-info/licenses/LICENSE
xGPR/__init__.py
xGPR/xgpr_cpu_rfgen_cpp_ext.cpython-312-x86_64-linux-gnu.so
xGPR/model_baseclass.py
xGPR/xgp_regression.py
xGPR/xgpr_cuda_rfgen_cpp_ext.cpython-312-x86_64-linux-gnu.so
xGPR/auxiliary_baseclass.py
xGPR/xgp_classification.py
xGPR/kernel_fgen.py
xGPR/random_feature_generation/__init__.py
xGPR/random_feature_generation/gpu_rf_gen/__init__.py
xGPR/random_feature_generation/gpu_rf_gen/sharedmem.h
xGPR/random_feature_generation/gpu_rf_gen/shared_constants.h
xGPR/random_feature_generation/gpu_rf_gen/xgpr_cuda_rfgen_cpp_ext.cpp
xGPR/random_feature_generation/gpu_rf_gen/basic_ops/basic_array_operations.cu
xGPR/random_feature_generation/gpu_rf_gen/basic_ops/__init__.py
xGPR/random_feature_generation/gpu_rf_gen/basic_ops/basic_array_operations.h
xGPR/random_feature_generation/gpu_rf_gen/rbf_ops/__init__.py
xGPR/random_feature_generation/gpu_rf_gen/rbf_ops/rbf_ops.h
xGPR/random_feature_generation/gpu_rf_gen/rbf_ops/rbf_ops.cu
xGPR/random_feature_generation/gpu_rf_gen/rbf_ops/ard_ops.cu
xGPR/random_feature_generation/gpu_rf_gen/rbf_ops/ard_ops.h
xGPR/random_feature_generation/gpu_rf_gen/convolution_ops/__init__.py
xGPR/random_feature_generation/gpu_rf_gen/convolution_ops/rbf_convolution.h
xGPR/random_feature_generation/gpu_rf_gen/convolution_ops/convolution.h
xGPR/random_feature_generation/gpu_rf_gen/convolution_ops/rbf_convolution.cu
xGPR/random_feature_generation/gpu_rf_gen/convolution_ops/convolution.cu
xGPR/random_feature_generation/gpu_rf_gen/classification_calcs/classification_calcs.cu
xGPR/random_feature_generation/gpu_rf_gen/classification_calcs/classification_calcs.h
xGPR/random_feature_generation/cpu_rf_gen/__init__.py
xGPR/random_feature_generation/cpu_rf_gen/xgpr_cpu_rfgen_cpp_ext.cpp
xGPR/random_feature_generation/cpu_rf_gen/.vscode/settings.json
xGPR/random_feature_generation/cpu_rf_gen/shared_fht_functions/__init__.py
