Metadata-Version: 2.1
Name: xGPR
Version: 0.4.8.5
Summary: Efficient approximate Bayesian machine learning
Keywords: xGPR,gaussian process,Gaussian process,Gaussian process regression,random Fourier features,approximate GP,GP,machine learning,Bayesian ML,random features
Author-Email: Jonathan Parkinson <jlparkinson1@gmail.com>
License: Academic Software Licence (“ASL”)
Project-URL: Homepage, https://github.com/jlparki/xGPR
Project-URL: Documentation, https://xgpr.readthedocs.io/en/latest/
Requires-Python: >=3.8
